{
    "schedule": [
        {
            "date": "Wednesday, October 29, 2025",
            "home_team": null,
            "away_team": null,
            "time": null,
            "location": null,
            "game_played": false,
            "final_score": null
        },
        {
            "date": "Thursday, October 30, 2025 - PLAYOFFS",
            "home_team": "Holy Cross",
            "away_team": "Father Bressani",
            "time": "3:30 PM",
            "location": "Holy Cross CA",
            "game_played": true,
            "final_score": "Holy Cross 2, Father Bressani 1"
        },
        {
            "date": "Thursday, October 30, 2025 - PLAYOFFS",
            "home_team": "St. Theresa Of Lisieux",
            "away_team": "Sacred Heart",
            "time": "3:30 PM",
            "location": "St Theresa Of Lisieux CHS",
            "game_played": true,
            "final_score": "St. Theresa Of Lisieux 5, Sacred Heart 0"
        },
        {
            "date": "Friday, October 31, 2025",
            "home_team": null,
            "away_team": null,
            "time": null,
            "location": null,
            "game_played": false,
            "final_score": null
        },
        {
            "date": "Saturday, November 1, 2025",
            "home_team": null,
            "away_team": null,
            "time": null,
            "location": null,
            "game_played": false,
            "final_score": null
        },
        {
            "date": "Sunday, November 2, 2025",
            "home_team": null,
            "away_team": null,
            "time": null,
            "location": null,
            "game_played": false,
            "final_score": null
        },
        {
            "date": "Monday, November 3, 2025",
            "home_team": null,
            "away_team": null,
            "time": null,
            "location": null,
            "game_played": false,
            "final_score": null
        },
        {
            "date": "Tuesday, November 4, 2025",
            "home_team": null,
            "away_team": null,
            "time": null,
            "location": null,
            "game_played": false,
            "final_score": null
        }
    ]
}