{
    "schedule": [
        {
            "date": "Monday, December 8, 2025",
            "home_team": "Bill Hogarth SS",
            "away_team": "Middlefield",
            "time": "4:45 PM",
            "location": "Bill Hogarth SS",
            "game_played": true,
            "final_score": "Bill Hogarth SS 66, Middlefield 69"
        },
        {
            "date": "Monday, December 8, 2025",
            "home_team": "Bur Oak SS",
            "away_team": "Father McGivney",
            "time": "4:45 PM",
            "location": "Bur Oak SS",
            "game_played": true,
            "final_score": "Bur Oak SS 72, Father McGivney 41"
        },
        {
            "date": "Monday, December 8, 2025",
            "home_team": "Dr. J.M. Denison",
            "away_team": "St. Maximilian",
            "time": "4:45 PM",
            "location": "Dr J M Denison SS",
            "game_played": true,
            "final_score": "Dr. J.M. Denison 51, St. Maximilian 74"
        },
        {
            "date": "Monday, December 8, 2025",
            "home_team": "Father Bressani",
            "away_team": "Holy Cross",
            "time": "3:30 PM",
            "location": "Father Bressani CHS",
            "game_played": true,
            "final_score": "Father Bressani 72, Holy Cross 56"
        },
        {
            "date": "Monday, December 8, 2025",
            "home_team": "Maple High School",
            "away_team": "Emily Carr",
            "time": "4:45 PM",
            "location": "Maple HS",
            "game_played": true,
            "final_score": "Maple High School 80, Emily Carr 54"
        },
        {
            "date": "Monday, December 8, 2025",
            "home_team": "Pierre Elliott Trudeau",
            "away_team": "St. Augustine",
            "time": "4:45 PM",
            "location": "PE Trudeau HS",
            "game_played": true,
            "final_score": "Pierre Elliott Trudeau 50, St. Augustine 52"
        },
        {
            "date": "Monday, December 8, 2025",
            "home_team": "Sir William Mulock",
            "away_team": "Huron Heights",
            "time": "3:45 PM",
            "location": "Sir William Mulock",
            "game_played": true,
            "final_score": "Sir William Mulock 62, Huron Heights 58"
        },
        {
            "date": "Tuesday, December 9, 2025",
            "home_team": "King City SS",
            "away_team": "Alexander Mackenzie",
            "time": "4:45 PM",
            "location": "King City SS",
            "game_played": true,
            "final_score": "King City SS 68, Alexander Mackenzie 60"
        },
        {
            "date": "Tuesday, December 9, 2025",
            "home_team": "Renaissance ESC",
            "away_team": "Cardinal Carter",
            "time": "4:45 PM",
            "location": "Renaissance ESC",
            "game_played": true,
            "final_score": "Renaissance ESC 55, Cardinal Carter 65"
        },
        {
            "date": "Tuesday, December 9, 2025",
            "home_team": "St. Katharine Drexel",
            "away_team": "Markville",
            "time": "4:45 PM",
            "location": "St Katharine Drexel CHS",
            "game_played": true,
            "final_score": "St. Katharine Drexel 27, Markville 94"
        },
        {
            "date": "Tuesday, December 9, 2025",
            "home_team": "St. Theresa Of Lisieux",
            "away_team": "Thornlea SS",
            "time": "4:45 PM",
            "location": "St Theresa Of Lisieux CHS",
            "game_played": true,
            "final_score": "St. Theresa Of Lisieux 81, Thornlea SS 75"
        },
        {
            "date": "Tuesday, December 9, 2025",
            "home_team": "Stephen Lewis SS",
            "away_team": "St. Robert",
            "time": "3:30 PM",
            "location": "Stephen Lewis SS",
            "game_played": true,
            "final_score": "Stephen Lewis SS 74, St. Robert 54"
        },
        {
            "date": "Tuesday, December 9, 2025",
            "home_team": "Unionville HS",
            "away_team": "Richmond Hill HS",
            "time": "4:45 PM",
            "location": "Unionville HS",
            "game_played": true,
            "final_score": "Unionville HS 73, Richmond Hill HS 77"
        },
        {
            "date": "Wednesday, December 10, 2025",
            "home_team": null,
            "away_team": null,
            "time": null,
            "location": null,
            "game_played": false,
            "final_score": null
        },
        {
            "date": "Thursday, December 11, 2025",
            "home_team": null,
            "away_team": null,
            "time": null,
            "location": null,
            "game_played": false,
            "final_score": null
        },
        {
            "date": "Friday, December 12, 2025",
            "home_team": null,
            "away_team": null,
            "time": null,
            "location": null,
            "game_played": false,
            "final_score": null
        },
        {
            "date": "Saturday, December 13, 2025",
            "home_team": null,
            "away_team": null,
            "time": null,
            "location": null,
            "game_played": false,
            "final_score": null
        },
        {
            "date": "Sunday, December 14, 2025",
            "home_team": null,
            "away_team": null,
            "time": null,
            "location": null,
            "game_played": false,
            "final_score": null
        }
    ]
}