{
    "schedule": [
        {
            "date": "Wednesday, November 26, 2025",
            "home_team": "St. Augustine",
            "away_team": "Bill Hogarth SS",
            "time": "2:30 PM",
            "location": "Angus Glen Arena",
            "game_played": true,
            "final_score": "St. Augustine 5, Bill Hogarth SS 3"
        },
        {
            "date": "Thursday, November 27, 2025",
            "home_team": null,
            "away_team": null,
            "time": null,
            "location": null,
            "game_played": false,
            "final_score": null
        },
        {
            "date": "Friday, November 28, 2025",
            "home_team": null,
            "away_team": null,
            "time": null,
            "location": null,
            "game_played": false,
            "final_score": null
        },
        {
            "date": "Saturday, November 29, 2025",
            "home_team": null,
            "away_team": null,
            "time": null,
            "location": null,
            "game_played": false,
            "final_score": null
        },
        {
            "date": "Sunday, November 30, 2025",
            "home_team": null,
            "away_team": null,
            "time": null,
            "location": null,
            "game_played": false,
            "final_score": null
        },
        {
            "date": "Monday, December 1, 2025",
            "home_team": null,
            "away_team": null,
            "time": null,
            "location": null,
            "game_played": false,
            "final_score": null
        },
        {
            "date": "Tuesday, December 2, 2025",
            "home_team": null,
            "away_team": null,
            "time": null,
            "location": null,
            "game_played": false,
            "final_score": null
        }
    ]
}